{"@context":"https://iiif.io/api/presentation/3/context.json","id":"https://abolition-now.github.io/an-ia-staging/api/facet/subject/art-from-the-insidecontrabandimmigrant-justice.json","type":"Collection","label":{"none":["Art from the Inside;Contraband;Immigrant Justice "]},"items":[{"id":"https://iiif.archive.org/iiif/an_0317_fawn/manifest.json","type":"Manifest","label":{"none":["Fawn"]},"thumbnail":[{"id":"https://iiif.archive.org/image/iiif/3/an_0317_fawn%2F0317_fawn_oo.png/full/332,/0/default.jpg","type":"Image","format":"image/jpeg","width":332,"height":327}],"homepage":[{"id":"https://abolition-now.github.io/an-ia-staging/works/fawn","type":"Text","label":{"none":["Fawn"]}}]}],"partOf":[{"id":"https://abolition-now.github.io/an-ia-staging/api/facet/subject.json","type":"Collection"}],"summary":{"none":["subject"]},"homepage":[{"id":"https://abolition-now.github.io/an-ia-staging/search?subject=art-from-the-insidecontrabandimmigrant-justice","type":"Text","label":{"none":["Art from the Inside;Contraband;Immigrant Justice "]}}]}