{"@context":"https://iiif.io/api/presentation/3/context.json","id":"https://abolition-now.github.io/an-ia-staging/api/facet/subject/communitydefend.json","type":"Collection","label":{"none":["Community;Defend"]},"items":[{"id":"https://iiif.archive.org/iiif/an_0004_defendourcommunities/manifest.json","type":"Manifest","label":{"none":["Defend Our Communities, Defund Police"]},"thumbnail":[{"id":"https://iiif.archive.org/image/iiif/3/an_0004_defendourcommunities%2F0004_defendourcommunities_oo.jpg/full/375,/0/default.jpg","type":"Image","format":"image/jpeg","width":375,"height":375}],"homepage":[{"id":"https://abolition-now.github.io/an-ia-staging/works/defend-our-communities-defund-police-2","type":"Text","label":{"none":["Defend Our Communities, Defund Police"]}}]}],"partOf":[{"id":"https://abolition-now.github.io/an-ia-staging/api/facet/subject.json","type":"Collection"}],"summary":{"none":["subject"]},"homepage":[{"id":"https://abolition-now.github.io/an-ia-staging/search?subject=communitydefend","type":"Text","label":{"none":["Community;Defend"]}}]}