{"@context":"https://iiif.io/api/presentation/3/context.json","id":"https://abolition-now.github.io/an-ia-staging/api/facet/visualmotifs/freedom-incarcerated-people-prisons.json","type":"Collection","label":{"none":["Freedom, Incarcerated People, Prisons"]},"items":[{"id":"https://iiif.archive.org/iiif/an_0028_endyouthincarceration/manifest.json","type":"Manifest","label":{"none":["End Youth Incarceration"]},"thumbnail":[{"id":"https://iiif.archive.org/image/iiif/3/an_0028_endyouthincarceration%2F0028_endyouthincarceration_oo.jpg/full/512,/0/default.jpg","type":"Image","format":"image/jpeg","width":512,"height":512}],"homepage":[{"id":"https://abolition-now.github.io/an-ia-staging/works/end-youth-incarceration","type":"Text","label":{"none":["End Youth Incarceration"]}}]},{"id":"https://iiif.archive.org/iiif/an_0005_freethemall/manifest.json","type":"Manifest","label":{"none":["Free Them All"]},"thumbnail":[{"id":"https://iiif.archive.org/image/iiif/3/an_0005_freethemall%2F0005_freethemall_oo.jpg/full/512,/0/default.jpg","type":"Image","format":"image/jpeg","width":512,"height":512}],"homepage":[{"id":"https://abolition-now.github.io/an-ia-staging/works/free-them-all-4","type":"Text","label":{"none":["Free Them All"]}}]}],"partOf":[{"id":"https://abolition-now.github.io/an-ia-staging/api/facet/visualmotifs.json","type":"Collection"}],"summary":{"none":["visual_motifs"]},"homepage":[{"id":"https://abolition-now.github.io/an-ia-staging/search?visualmotifs=freedom-incarcerated-people-prisons","type":"Text","label":{"none":["Freedom, Incarcerated People, Prisons"]}}]}